[
    {
        "Date": "Saturday, July 01",
        "Time": "No Appointments"
    },
    {
        "Date": "Sunday, July 02",
        "Time": "No Appointments"
    },
    {
        "Date": "Monday, July 03",
        "Time": "No Appointments"
    },
    {
        "Date": "Tuesday, July 04",
        "Time": "No Appointments"
    },
    {
        "Date": "Wednesday, July 05",
        "Time": [
            "12pm"
        ]
    },
    {
        "Date": "Thursday, July 06",
        "Time": [
            "10:30am",
            "11am",
            "11:30am",
            "12pm",
            "12:30pm",
            "1pm",
            "1:30pm",
            "2pm",
            "2:30pm",
            "3pm",
            "3:30pm",
            "4pm",
            "7:30pm"
        ]
    },
    {
        "Date": "Friday, July 07",
        "Time": "No Appointments"
    }
]